rkd/__init__.py
rkd/__main__.py
rkd/argparsing.py
rkd/context.py
rkd/contract.py
rkd/exception.py
rkd/executor.py
rkd/inputoutput.py
rkd/process.py
rkd/resolver.py
rkd/results.py
rkd/syntax.py
rkd/taskutil.py
rkd/test.py
rkd/validator.py
rkd/yaml_context.py
rkd/internal/makefile.py
rkd/misc/banner.txt
rkd/misc/initial-structure/.rkd/makefile.py
rkd/standardlib/__init__.py
rkd/standardlib/docker.py
rkd/standardlib/python.py
rkd/standardlib/shell.py
rkd-0.3.1.dist-info/AUTHORS
rkd-0.3.1.dist-info/METADATA
rkd-0.3.1.dist-info/WHEEL
rkd-0.3.1.dist-info/entry_points.txt
rkd-0.3.1.dist-info/pbr.json
rkd-0.3.1.dist-info/top_level.txt
rkd-0.3.1.dist-info/RECORD
