Metadata-Version: 2.1
Name: rkd
Version: 0.3.1
Summary: Task executor - balance between Makefile and Gradle.
Home-page: https://riotkit.org
Author: RiotKit non-profit organization
Author-email: riotkit@riseup.net
License: Apache-2
Keywords: setup,distutils
Platform: UNKNOWN
Classifier: Development Status :: 4 - Beta
Classifier: Environment :: Console
Classifier: Intended Audience :: Developers
Classifier: Intended Audience :: Information Technology
Classifier: License :: OSI Approved :: Apache Software License
Classifier: Operating System :: OS Independent
Classifier: Programming Language :: Python
Requires-Dist: twine (==3.1.1)
Requires-Dist: pbr (==5.4.5)
Requires-Dist: jinja2 (>=2.11)
Requires-Dist: pyyaml (>=5.3.1)
